teler/__init__.py
teler/exceptions.py
teler/streams.py
teler-0.1.0.dist-info/licenses/LICENSE
teler-0.1.0.dist-info/METADATA
teler-0.1.0.dist-info/WHEEL
teler-0.1.0.dist-info/top_level.txt
teler-0.1.0.dist-info/RECORD
