Metadata-Version: 2.4
Name: teler
Version: 0.1.0
Summary: A helper library for FreJun Teler
Author-email: FreJun <hello@frejun.com>
License: MIT License
License-File: LICENSE
Requires-Dist: websockets>=10.0
Dynamic: license-file
